setup.py
Arduino/__init__.py
Arduino/arduino.py
arduino_python.egg-info/PKG-INFO
arduino_python.egg-info/SOURCES.txt
arduino_python.egg-info/dependency_links.txt
arduino_python.egg-info/requires.txt
arduino_python.egg-info/top_level.txt