Metadata-Version: 1.0
Name: arduino-python
Version: 0.2
Summary: A light-weight Python library that provides a serial       bridge for communicating with Arduino microcontroller boards
Home-page: https://github.com/thearn/Python-Arduino-Command-API
Author: Tristan Hearn
Author-email: tristanhearn@gmail.com
License: Apache 2.0
Platform: UNKNOWN
